vaikerai/__about__.py
vaikerai/__init__.py
vaikerai/account.py
vaikerai/client.py
vaikerai/collection.py
vaikerai/deployment.py
vaikerai/exceptions.py
vaikerai/files.py
vaikerai/hardware.py
vaikerai/identifier.py
vaikerai/json.py
vaikerai/model.py
vaikerai/pagination.py
vaikerai/prediction.py
vaikerai/resource.py
vaikerai/run.py
vaikerai/schema.py
vaikerai/stream.py
vaikerai/training.py
vaikerai/version.py
vaikerai/webhook.py
vaikerai-0.0.1.dist-info/LICENSE
vaikerai-0.0.1.dist-info/METADATA
vaikerai-0.0.1.dist-info/WHEEL
vaikerai-0.0.1.dist-info/top_level.txt
vaikerai-0.0.1.dist-info/RECORD
