Metadata-Version: 2.1
Name: vaikerai
Version: 0.0.1
Summary: Python client for vaikerai
Author: vaikerai, Inc.
License: 
Project-URL: homepage, https://vaikerai.com
Project-URL: repository, https://github.com/vaikerai/vaikerai-python
Requires-Python: >=3.8
License-File: LICENSE
Requires-Dist: httpx<1,>=0.21.0
Requires-Dist: packaging
Requires-Dist: pydantic>1.10.7
Requires-Dist: typing-extensions>=4.5.0
